buckaroo/__init__.py
buckaroo/_version.py
buckaroo/buckaroo_widget.py
buckaroo/ddd_library.py
buckaroo/df_util.py
buckaroo/extension_utils.py
buckaroo/geopandas_buckaroo.py
buckaroo/lazy_infinite_polars_widget.py
buckaroo/marimo_utils.py
buckaroo/polars_buckaroo.py
buckaroo/read_utils.py
buckaroo/serialization_utils.py
buckaroo/solara_buckaroo.py
buckaroo/styling_helpers.py
buckaroo/trait_utils.py
buckaroo/widget_class_utils.py
buckaroo/widget_utils.py
buckaroo/auto_clean/__init__.py
buckaroo/auto_clean/auto_clean.py
buckaroo/auto_clean/cleaning_commands.py
buckaroo/auto_clean/heuristic_lang.py
buckaroo/contrib/__init__.py
buckaroo/contrib/buckaroo_pandera.py
buckaroo/customizations/__init__.py
buckaroo/customizations/all_transforms.py
buckaroo/customizations/analysis.py
buckaroo/customizations/analysis_utils.py
buckaroo/customizations/heuristics.py
buckaroo/customizations/histogram.py
buckaroo/customizations/order_columns.py
buckaroo/customizations/pandas_cleaning_commands.py
buckaroo/customizations/pandas_commands.py
buckaroo/customizations/pd_autoclean_conf.py
buckaroo/customizations/pd_fracs.py
buckaroo/customizations/pl_autocleaning_conf.py
buckaroo/customizations/polars_analysis.py
buckaroo/customizations/polars_commands.py
buckaroo/customizations/styling.py
buckaroo/dataflow/__init__.py
buckaroo/dataflow/abc_dataflow.py
buckaroo/dataflow/autocleaning.py
buckaroo/dataflow/column_executor_dataflow.py
buckaroo/dataflow/dataflow.py
buckaroo/dataflow/dataflow_extras.py
buckaroo/dataflow/styling_core.py
buckaroo/dataflow/widget_extension_utils.py
buckaroo/file_cache/__init__.py
buckaroo/file_cache/base.py
buckaroo/file_cache/batch_planning.py
buckaroo/file_cache/bisector.py
buckaroo/file_cache/cache_utils.py
buckaroo/file_cache/mp_calibration.py
buckaroo/file_cache/mp_timeout_decorator.py
buckaroo/file_cache/multiprocessing_executor.py
buckaroo/file_cache/paf_column_executor.py
buckaroo/file_cache/sqlite_file_cache.py
buckaroo/file_cache/sqlite_log.py
buckaroo-0.12.4.dist-info/METADATA
buckaroo-0.12.4.dist-info/WHEEL
buckaroo-0.12.4.dist-info/licenses/LICENSE.txt
buckaroo-0.12.4.dist-info/RECORD
