Metadata-Version: 2.4
Name: buckaroo
Version: 0.12.4
Summary: Buckaroo - GUI Data wrangling for pandas
Project-URL: Homepage, https://github.com/paddymul/buckaroo
Author: Paddy Mullen
License: Copyright (c) 2019 Bloomberg
License-File: LICENSE.txt
Keywords: IPython,Jupyter,Widgets,pandas
Classifier: Framework :: Jupyter
Classifier: Framework :: Jupyter :: JupyterLab
Classifier: Framework :: Jupyter :: JupyterLab :: Extensions
Classifier: Intended Audience :: Developers
Classifier: Intended Audience :: Science/Research
Classifier: License :: OSI Approved :: BSD License
Classifier: Programming Language :: Python
Classifier: Programming Language :: Python :: 3
Classifier: Programming Language :: Python :: 3 :: Only
Classifier: Programming Language :: Python :: 3.10
Requires-Python: >=3.11
Requires-Dist: anywidget>=0.9.0
Requires-Dist: cloudpickle>=3.1.1
Requires-Dist: fastparquet
Requires-Dist: graphlib-backport>=1.0.0
Requires-Dist: pyarrow>=18.0.0
Provides-Extra: dev
Requires-Dist: anywidget[dev]>=0.9.0; extra == 'dev'
Requires-Dist: graphviz>=0.20.1; extra == 'dev'
Requires-Dist: hypothesis>=6.88.1; extra == 'dev'
Requires-Dist: jupyterlab>=4.2.5; extra == 'dev'
Requires-Dist: mistune<3.1; extra == 'dev'
Requires-Dist: nbval>=0.9; extra == 'dev'
Requires-Dist: pandas>=1.3.5; extra == 'dev'
Requires-Dist: pl-series-hash==0.2.1; extra == 'dev'
Requires-Dist: playwright; extra == 'dev'
Requires-Dist: pyarrow; extra == 'dev'
Requires-Dist: pydantic>=2.5.2; extra == 'dev'
Requires-Dist: pytest; extra == 'dev'
Requires-Dist: pytest-check-links; extra == 'dev'
Requires-Dist: pytest-playwright; extra == 'dev'
Requires-Dist: ruff>=0.6.2; extra == 'dev'
Requires-Dist: solara; extra == 'dev'
Requires-Dist: solara[pytest]; extra == 'dev'
Requires-Dist: sphinx>=1.5; extra == 'dev'
Requires-Dist: toml; extra == 'dev'
Requires-Dist: watchfiles; extra == 'dev'
Provides-Extra: jupyterlab
Requires-Dist: jupyterlab>=3.6.0; extra == 'jupyterlab'
Provides-Extra: notebook
Requires-Dist: notebook>=7.0.0; extra == 'notebook'
Provides-Extra: packaging-tools
Requires-Dist: build; extra == 'packaging-tools'
Requires-Dist: twine; extra == 'packaging-tools'
Provides-Extra: polars
Requires-Dist: pl-series-hash==0.2.1; extra == 'polars'
Requires-Dist: polars; extra == 'polars'
Requires-Dist: polars>=1.24.0; extra == 'polars'
Requires-Dist: polars[timezone]; extra == 'polars'
Provides-Extra: test
Requires-Dist: anywidget; extra == 'test'
Requires-Dist: codecov; extra == 'test'
Requires-Dist: hypothesis>=6.88.1; extra == 'test'
Requires-Dist: nbstripout; extra == 'test'
Requires-Dist: nbval>=0.9; extra == 'test'
Requires-Dist: pandas>=1.3.5; extra == 'test'
Requires-Dist: pandera; extra == 'test'
Requires-Dist: pydantic>=2.5.2; extra == 'test'
Requires-Dist: pytest-cov>=3; extra == 'test'
Requires-Dist: pytest>=6; extra == 'test'
Requires-Dist: ruff; extra == 'test'
